{
    "$schema": "https://schema.management.azure.com/schemas/2019-04-01/deploymentTemplate.json#",
    "contentVersion": "1.0.0.0",
    "parameters": {
        "appLocation": {
            "type": "string"
        },
        "environment": {
            "type": "string"
        },
        "dbName": {
            "type": "string"
        }
    },
    "variables": {
        "fulldbName": "[concat(parameters('dbName'), parameters('environment'))]"
    },
    "resources": [
        {
            "type": "Microsoft.DocumentDB/databaseAccounts",
            "apiVersion": "2023-11-15",
            "name": "[variables('fulldbName')]",
            "location": "[parameters('appLocation')]",
            "kind": "GlobalDocumentDB",
            "identity": {
                "type": "None"
            },
            "properties": {
                "publicNetworkAccess": "Enabled",
                "enableAutomaticFailover": false,
                "enableMultipleWriteLocations": false,
                "isVirtualNetworkFilterEnabled": false,
                "disableKeyBasedMetadataWriteAccess": false,
                "enableFreeTier": false,
                "enableAnalyticalStorage": false,
                "analyticalStorageConfiguration": {
                    "schemaType": "WellDefined"
                },
                "createMode": "Default",
                "databaseAccountOfferType": "Standard",
                "defaultIdentity": "FirstPartyIdentity",
                "networkAclBypass": "None",
                "disableLocalAuth": false,
                "enablePartitionMerge": false,
                "enableBurstCapacity": false,
                "minimalTlsVersion": "Tls12",
                "consistencyPolicy": {
                    "defaultConsistencyLevel": "Session",
                    "maxIntervalInSeconds": 5,
                    "maxStalenessPrefix": 100
                },
                "locations": [
                    {
                        "failoverPriority": 0,
                        "isZoneRedundant": false
                    }
                ],
                "cors": [],
                "capabilities": [
                    {
                        "name": "EnableServerless"
                    }
                ],
                "backupPolicy": {
                    "type": "Continuous",
                    "continuousModeProperties": {
                        "tier": "Continuous7Days"
                    }
                },
                "capacity": {
                    "totalThroughputLimit": 4000
                }
            }
        },
        {
            "type": "Microsoft.DocumentDB/databaseAccounts/sqlDatabases",
            "apiVersion": "2023-11-15",
            "name": "[concat(variables('fulldbName'), '/VisitCount')]",
            "dependsOn": [
                "[resourceId('Microsoft.DocumentDB/databaseAccounts', variables('fulldbName'))]"
            ],
            "properties": {
                "resource": {
                    "id": "VisitCount"
                }
            }
        }
    ]
}